cognee_integration_google_adk/__init__.py
cognee_integration_google_adk/bootstrap.py
cognee_integration_google_adk/tools.py
cognee_integration_google_adk-0.1.1.dist-info/METADATA
cognee_integration_google_adk-0.1.1.dist-info/WHEEL
cognee_integration_google_adk-0.1.1.dist-info/top_level.txt
cognee_integration_google_adk-0.1.1.dist-info/RECORD
