Metadata-Version: 2.4
Name: cognee-integration-google-adk
Version: 0.1.1
Summary: Integrate Cognee's memory system seamlessly with your Google ADK agent using easy-to-use tools.
Requires-Python: >=3.10
Requires-Dist: cognee>=0.4.0
Requires-Dist: google-adk>=1.19.0
Requires-Dist: python-dotenv>=1.2.1
